AUTHORS.md
CONTRIBUTING.md
HISTORY.md
LICENSE
MANIFEST.in
README.md
setup.cfg
setup.py
custom_settings/__init__.py
custom_settings/loader.py
django_custom_settings.egg-info/PKG-INFO
django_custom_settings.egg-info/SOURCES.txt
django_custom_settings.egg-info/dependency_links.txt
django_custom_settings.egg-info/not-zip-safe
django_custom_settings.egg-info/requires.txt
django_custom_settings.egg-info/top_level.txt