Metadata-Version: 1.1
Name: django-custom-settings
Version: 0.1.4
Summary: Custom settings loader for standalone django apps
Home-page: https://sigmageosistemas.com.br/dev/django-custom-settings
Author: Sigma Geosistemas LTDA
Author-email: atendimento@sigmageosistemas.com.br
License: MIT
Keywords: django-custom-settings
Platform: UNKNOWN
Classifier: Development Status :: 3 - Alpha
Classifier: Framework :: Django
Classifier: Framework :: Django :: 1.8
Classifier: Framework :: Django :: 1.9
Classifier: Intended Audience :: Developers
Classifier: License :: OSI Approved :: BSD License
Classifier: Natural Language :: English
Classifier: Programming Language :: Python :: 2
Classifier: Programming Language :: Python :: 2.7
Classifier: Programming Language :: Python :: 3
Classifier: Programming Language :: Python :: 3.3
Classifier: Programming Language :: Python :: 3.4
Classifier: Programming Language :: Python :: 3.5
